{"cameraMode":{"drawMode":0,"name":"Shaded","section":"Shading Mode"},"sceneLighting":true,"audioPlay":false,"sceneViewState":{"showFog":true,"showMaterialUpdate":false,"showSkybox":false,"showFlares":true,"showImageEffects":true,"showParticleSystems":true,"showVisualEffectGraphs":true,"m_FxEnabled":true},"in2DMode":false,"pivot":{"x":5.232363700866699,"y":2.6966304779052736,"z":2.2631893157958986},"rotation":{"x":0.29335877299308779,"y":-0.6967270970344544,"z":0.38726237416267397,"w":0.527778148651123},"size":4.39835786819458,"orthographic":false}